[
    {
        "Author": "yoinky",
        "Name": "PuppetMaster",
        "Description": "A short one-liner that shows up in /xlplugins.",
        "InternalName": "PuppetMaster",
        "AssemblyVersion": "0.0.0.1",
        "TestingAssemblyVersion": "0.0.0.1",
        "RepoUrl": "https://github.com/Estrogen-Rocks/wahoo/new/main",
        "ApplicableVersion": "any",
        "DalamudApiLevel": 9,
        "IsHide": "False",
        "IsTestingExclusive": "False",
        "DownloadCount": 0,
        "LastUpdate": 0,
        "LoadPriority": 69420,
        "DownloadLinkInstall": "https://github.com/Estrogen-Rocks/wahoo/raw/main/latest.zip",
        "DownloadLinkTesting": "https://github.com/Estrogen-Rocks/wahoo/raw/main/latest.zip",
        "DownloadLinkUpdate": "https://github.com/Estrogen-Rocks/wahoo/raw/main/latest.zip",
    }
]
